swarmauri_crypto_jwe/JweCrypto.py
swarmauri_crypto_jwe/__init__.py
swarmauri_crypto_jwe-0.2.0.dev4.dist-info/LICENSE
swarmauri_crypto_jwe-0.2.0.dev4.dist-info/METADATA
swarmauri_crypto_jwe-0.2.0.dev4.dist-info/WHEEL
swarmauri_crypto_jwe-0.2.0.dev4.dist-info/RECORD
