Metadata-Version: 2.3
Name: swarmauri_crypto_jwe
Version: 0.2.0.dev4
Summary: RFC 7516/7518 compliant JWE crypto provider for Swarmauri
License: Apache-2.0
Author: Swarmauri
Author-email: opensource@swarmauri.com
Requires-Python: >=3.10,<3.13
Classifier: License :: OSI Approved :: Apache Software License
Classifier: Natural Language :: English
Classifier: Programming Language :: Python :: 3.10
Classifier: Programming Language :: Python :: 3.11
Classifier: Programming Language :: Python :: 3.12
Classifier: Programming Language :: Python :: 3.13
Classifier: Development Status :: 3 - Alpha
Classifier: Topic :: Security :: Cryptography
Classifier: Intended Audience :: Developers
Provides-Extra: cbor
Provides-Extra: json
Requires-Dist: cbor2 ; extra == "cbor"
Requires-Dist: cryptography (>=41)
Requires-Dist: swarmauri_base
Requires-Dist: swarmauri_core
